{"version":"0.4","title":"P4 \u2013 Text Left Image Right with CTA","type":"page","content":[{"id":"17904c8f","settings":{"section_layout":"","layout":"full_width","gap":"no","height":"full","custom_height":{"unit":"px","size":"800"},"content_position":"middle","structure":"20","section_background":"","background_background":"classic","background_color":"#ffffff","background_position":"center right","background_repeat":"no-repeat","background_size":"auto","background_overlay_title":"","section_border":"","box_shadow_box_shadow":{"horizontal":0,"vertical":0,"blur":10,"spread":0,"inset":"","color":"rgba(0,0,0,0.5)"},"section_typo":"","section_advanced":"","padding_mobile":{"unit":"px","top":"60","right":"30","bottom":"60","left":"30","isLinked":false},"_section_responsive":"","heading_visibility":"","responsive_description":"","background_overlay_section":""},"elements":[{"id":"e60fe85","settings":{"_column_size":50,"_inline_size":null,"section_style":"","box_shadow_box_shadow":{"horizontal":0,"vertical":0,"blur":10,"spread":0,"inset":"","color":"rgba(0,0,0,0.5)"},"section_typo":"","section_advanced":"","padding":{"unit":"%","top":"0","right":"5","bottom":"0","left":"20","isLinked":false},"padding_mobile":{"unit":"px","top":"0","right":"0","bottom":"0","left":"0","isLinked":true},"section_responsive":"","screen_xs":"default","screen_xs_width":"100"},"elements":[{"id":"5da57fda","settings":{"section_title":"","title":"Try it Yourself","link":{"is_external":"","url":""},"size":"large","header_size":"h3","align_mobile":"center","section_title_style":"","title_color":"#282828","typography_typography":"custom","typography_font_size":{"unit":"px","size":63},"typography_font_family":"Poppins","typography_line_height_tablet":{"unit":"em","size":""},"typography_line_height_mobile":{"unit":"em","size":""},"typography_letter_spacing":{"unit":"px","size":"-3"},"_section_style":"","_padding":{"unit":"px","top":"0","right":"0","bottom":"0","left":"0","isLinked":true},"_section_background":"","_box_shadow_box_shadow":{"horizontal":0,"vertical":0,"blur":10,"spread":0,"inset":"","color":"rgba(0,0,0,0.5)"},"_section_responsive":"","responsive_description":""},"elements":[],"isInner":false,"widgetType":"heading","elType":"widget"},{"id":"3f84b88d","settings":{"section_editor":"","editor":"<p>What makes design\u00a0so alluring? We\u00a0believes the answer is designers. That's why we have made\u00a0our entire focus on you - the designer. Your style, your ideas, your creativity.\u00a0Go on -\u00a0Try, share and design now!<\/p>","section_style":"","align_mobile":"center","typography_typography":"custom","typography_font_size":{"unit":"px","size":"17"},"typography_font_family":"Lora","typography_line_height":{"unit":"em","size":1.8},"typography_line_height_tablet":{"unit":"em","size":""},"typography_line_height_mobile":{"unit":"em","size":""},"_section_style":"","_padding":{"unit":"px","top":"20","right":"0","bottom":"20","left":"0","isLinked":false},"_padding_mobile":{"unit":"px","top":"0","right":"0","bottom":"0","left":"0","isLinked":false},"_section_background":"","_box_shadow_box_shadow":{"horizontal":0,"vertical":0,"blur":10,"spread":0,"inset":"","color":"rgba(0,0,0,0.5)"},"_section_responsive":"","responsive_description":""},"elements":[],"isInner":false,"widgetType":"text-editor","elType":"widget"},{"id":"76353737","settings":{"section_button":"","text":"Get Started","link":{"is_external":"","url":"#"},"align_mobile":"center","icon":"fa fa-angle-right","icon_align":"right","icon_indent":{"unit":"px","size":16},"section_style":"","typography_typography":"custom","typography_font_family":"Poppins","typography_font_weight":"500","typography_line_height":{"unit":"em","size":"1"},"typography_line_height_tablet":{"unit":"em","size":""},"typography_line_height_mobile":{"unit":"em","size":""},"typography_letter_spacing":{"unit":"px","size":0.7},"border_radius":{"unit":"px","top":"50","right":"50","bottom":"50","left":"50","isLinked":true},"text_padding":{"unit":"px","top":"15","right":"40","bottom":"15","left":"40","isLinked":false},"section_hover":"","button_background_hover_color":"#000000","_section_style":"","_section_background":"","_box_shadow_box_shadow":{"horizontal":0,"vertical":0,"blur":10,"spread":0,"inset":"","color":"rgba(0,0,0,0.5)"},"_section_responsive":"","responsive_description":""},"elements":[],"isInner":false,"widgetType":"button","elType":"widget"}],"isInner":false,"elType":"column"},{"id":"7852f31a","settings":{"_column_size":50,"_inline_size":null,"section_style":"","box_shadow_box_shadow":{"horizontal":0,"vertical":0,"blur":10,"spread":0,"inset":"","color":"rgba(0,0,0,0.5)"},"section_typo":"","section_advanced":"","section_responsive":"","screen_xs":"default","screen_xs_width":"100"},"elements":[{"id":"7a4b12a1","settings":{"section_image":"","image":{"id":"52","url":"http:\/\/www.tyler.com\/wp-content\/uploads\/2017\/11\/ma.png"},"align":"right","align_tablet":"center","align_mobile":"center","link":{"is_external":"","url":""},"section_style_image":"","space":{"unit":"%","size":90},"image_box_shadow_box_shadow":{"horizontal":0,"vertical":0,"blur":10,"spread":0,"inset":"","color":"rgba(0,0,0,0.5)"},"section_style_caption":"","caption_align":"right","caption_typography_line_height_tablet":{"unit":"em","size":""},"caption_typography_line_height_mobile":{"unit":"em","size":""},"_section_style":"","_section_background":"","_box_shadow_box_shadow":{"horizontal":0,"vertical":0,"blur":10,"spread":0,"inset":"","color":"rgba(0,0,0,0.5)"},"_section_responsive":"","responsive_description":"","hide_mobile":"hidden-phone","image_size":"full"},"elements":[],"isInner":false,"widgetType":"image","elType":"widget"}],"isInner":false,"elType":"column"}],"isInner":false,"elType":"section"}]}